[
    {
        "jobTitle": "  Front-end Engineer (Contractor)\n\n",
        "company": "Mastercard",
        "source": "LinkedIn",
        "date": "2018-9-11",
        "category": "",
        "url": "https://www.linkedin.com/jobs/view/827664306",
        "jobLikes": 0
    },
    {
        "jobTitle": "  Lead Front End Engineer\n\n",
        "company": "Flare Emergency Response",
        "source": "LinkedIn",
        "date": "2018-9-11",
        "category": "",
        "url": "https://www.linkedin.com/jobs/view/705071011",
        "jobLikes": 0
    },
    {
        "jobTitle": "  FRONT END DEVELOPER\n\n",
        "company": "RMPG",
        "source": "LinkedIn",
        "date": "2018-9-11",
        "category": "",
        "url": "https://www.linkedin.com/jobs/view/845111165",
        "jobLikes": 0
    },
    {
        "jobTitle": "",
        "company": "",
        "source": "LinkedIn",
        "date": "2018-9-11",
        "category": "",
        "url": "https://www.linkedin.com/jobs/view/undefined",
        "jobLikes": 0
    },
    {
        "jobTitle": "  Kibana - JavaScript Engineer in Test\n\n",
        "company": "Elastic",
        "source": "LinkedIn",
        "date": "2018-9-11",
        "category": "",
        "url": "https://www.linkedin.com/jobs/view/836891399",
        "jobLikes": 0
    },
    {
        "jobTitle": "  Senior Software Engineer (Android/Java)\n\n",
        "company": "Ona Data",
        "source": "LinkedIn",
        "date": "2018-9-11",
        "category": "",
        "url": "https://www.linkedin.com/jobs/view/849447278",
        "jobLikes": 0
    },
    {
        "jobTitle": "  Full Stack Developer\n\n",
        "company": "Exceed Human Resource Consultants",
        "source": "LinkedIn",
        "date": "2018-9-11",
        "category": "",
        "url": "https://www.linkedin.com/jobs/view/845108355",
        "jobLikes": 0
    },
    {
        "jobTitle": "  Duma Works Job Vacancy : PHP & Laravel Developer\n\n",
        "company": "Duma Works",
        "source": "LinkedIn",
        "date": "2018-9-11",
        "category": "",
        "url": "https://www.linkedin.com/jobs/view/857656757",
        "jobLikes": 0
    },
    {
        "jobTitle": "  Junior software developer\n\n",
        "company": "Star Personnel Inc.",
        "source": "LinkedIn",
        "date": "2018-9-11",
        "category": "",
        "url": "https://www.linkedin.com/jobs/view/845108400",
        "jobLikes": 0
    },
    {
        "jobTitle": "  Senior Java Developer\n\n",
        "company": "Parvana",
        "source": "LinkedIn",
        "date": "2018-9-11",
        "category": "",
        "url": "https://www.linkedin.com/jobs/view/855118292",
        "jobLikes": 0
    },
    {
        "jobTitle": "  Junior PHP Web Developer, Somerset West\n\n",
        "company": "Spencer Rogers Recruitment Consultants",
        "source": "LinkedIn",
        "date": "2018-9-11",
        "category": "",
        "url": "https://www.linkedin.com/jobs/view/856069090",
        "jobLikes": 0
    },
    {
        "jobTitle": "  Frank Management Job Vacancy : Software Developer\n\n",
        "company": "Frank Management",
        "source": "LinkedIn",
        "date": "2018-9-11",
        "category": "",
        "url": "https://www.linkedin.com/jobs/view/856365902",
        "jobLikes": 0
    },
    {
        "jobTitle": "  IT Support Representative\n\n",
        "company": "Radiometer",
        "source": "LinkedIn",
        "date": "2018-9-11",
        "category": "",
        "url": "https://www.linkedin.com/jobs/view/839467814",
        "jobLikes": 0
    },
    {
        "jobTitle": "  IntSoft (K) Limited Job Vacancy : Software Developer\n\n",
        "company": "IntSoft (K) Limited",
        "source": "LinkedIn",
        "date": "2018-9-11",
        "category": "",
        "url": "https://www.linkedin.com/jobs/view/839565648",
        "jobLikes": 0
    },
    {
        "jobTitle": "  Mid-level Android Developer – Cape Town –From R400k Per Annum\n\n",
        "company": "e-Merge IT Recruitment",
        "source": "LinkedIn",
        "date": "2018-9-11",
        "category": "",
        "url": "https://www.linkedin.com/jobs/view/855119544",
        "jobLikes": 0
    },
    {
        "jobTitle": "  Sportpesa Job Vacancy : SharePoint Administrator\n\n",
        "company": "Sportpesa",
        "source": "LinkedIn",
        "date": "2018-9-11",
        "category": "",
        "url": "https://www.linkedin.com/jobs/view/853991807",
        "jobLikes": 0
    },
    {
        "jobTitle": "  Senior Full Stack Developer\n\n",
        "company": "Mass Staffing Projects",
        "source": "LinkedIn",
        "date": "2018-9-11",
        "category": "",
        "url": "https://www.linkedin.com/jobs/view/845108980",
        "jobLikes": 0
    },
    {
        "jobTitle": "  Developer (Blaauwberg, Cape Town) R400 – R650 ph\n\n",
        "company": "West Coast Personnel",
        "source": "LinkedIn",
        "date": "2018-9-11",
        "category": "",
        "url": "https://www.linkedin.com/jobs/view/845128810",
        "jobLikes": 0
    },
    {
        "jobTitle": "  INFORMATION TECHNOLOGY ASSISTANT\n\n",
        "company": "United Nations",
        "source": "LinkedIn",
        "date": "2018-9-11",
        "category": "",
        "url": "https://www.linkedin.com/jobs/view/836029550",
        "jobLikes": 0
    },
    {
        "jobTitle": "  Business Analyst\n\n",
        "company": "UAP OLD MUTUAL GROUP",
        "source": "LinkedIn",
        "date": "2018-9-11",
        "category": "",
        "url": "https://www.linkedin.com/jobs/view/839454374",
        "jobLikes": 0
    },
    {
        "jobTitle": "  Platform Engineers\n\n",
        "company": "mSurvey™",
        "source": "LinkedIn",
        "date": "2018-9-11",
        "category": "",
        "url": "https://www.linkedin.com/jobs/view/827672978",
        "jobLikes": 0
    },
    {
        "jobTitle": "  Maasai Mara University Job Vacancy : Computer Laboratory Assistants\n\n",
        "company": "The MAASAI Group, LLC",
        "source": "LinkedIn",
        "date": "2018-9-11",
        "category": "",
        "url": "https://www.linkedin.com/jobs/view/853992572",
        "jobLikes": 0
    },
    {
        "jobTitle": "  Senior Software Engineer - DevOps\n\n",
        "company": "Gro Intelligence",
        "source": "LinkedIn",
        "date": "2018-9-11",
        "category": "",
        "url": "https://www.linkedin.com/jobs/view/833401280",
        "jobLikes": 0
    },
    {
        "jobTitle": "  Sheer Logic Job Vacancy : Computer Programmer\n\n",
        "company": "Sheer Logic",
        "source": "LinkedIn",
        "date": "2018-9-11",
        "category": "",
        "url": "https://www.linkedin.com/jobs/view/839565627",
        "jobLikes": 0
    },
    {
        "jobTitle": "  Kenya Field Operations Deliveries Associate\n\n",
        "company": "One Acre Fund",
        "source": "LinkedIn",
        "date": "2018-9-11",
        "category": "",
        "url": "https://www.linkedin.com/jobs/view/836531753",
        "jobLikes": 0
    }
]